DOCKER.md
MANIFEST.in
pyproject.toml
requirements-package.txt
requirements-runtime.txt
requirements-test.txt
requirements-typehint.txt
localstack/pro/core/__init__.py
localstack/pro/core/config.py
localstack/pro/core/constants.py
localstack/pro/core/openapi.yaml
localstack/pro/core/plugins.py
localstack/pro/core/providers.py
localstack/pro/core/version.py
localstack/pro/core/analytics/__init__.py
localstack/pro/core/analytics/aws_request_aggregator.py.enc
localstack/pro/core/analytics/aws_request_logger.py.enc
localstack/pro/core/analytics/plugins.py
localstack/pro/core/aws/__init__.py
localstack/pro/core/aws/plugins.py
localstack/pro/core/aws/api/__init__.py
localstack/pro/core/aws/api/account/__init__.py
localstack/pro/core/aws/api/acm_pca/__init__.py
localstack/pro/core/aws/api/amplify/__init__.py
localstack/pro/core/aws/api/apigatewaymanagementapi/__init__.py
localstack/pro/core/aws/api/apigatewayv2/__init__.py
localstack/pro/core/aws/api/appconfig/__init__.py
localstack/pro/core/aws/api/appconfigdata/__init__.py
localstack/pro/core/aws/api/application_autoscaling/__init__.py
localstack/pro/core/aws/api/appsync/__init__.py
localstack/pro/core/aws/api/athena/__init__.py
localstack/pro/core/aws/api/autoscaling/__init__.py
localstack/pro/core/aws/api/backup/__init__.py
localstack/pro/core/aws/api/batch/__init__.py
localstack/pro/core/aws/api/bedrock/__init__.py
localstack/pro/core/aws/api/bedrock_runtime/__init__.py
localstack/pro/core/aws/api/ce/__init__.py
localstack/pro/core/aws/api/cloudfront/__init__.py
localstack/pro/core/aws/api/cloudtrail/__init__.py
localstack/pro/core/aws/api/codebuild/__init__.py
localstack/pro/core/aws/api/codecommit/__init__.py
localstack/pro/core/aws/api/codedeploy/__init__.py
localstack/pro/core/aws/api/codepipeline/__init__.py
localstack/pro/core/aws/api/cognito_identity/__init__.py
localstack/pro/core/aws/api/cognito_idp/__init__.py
localstack/pro/core/aws/api/dms/__init__.py
localstack/pro/core/aws/api/ecr/__init__.py
localstack_ext.egg-info/PKG-INFO
localstack_ext.egg-info/SOURCES.txt
localstack_ext.egg-info/dependency_links.txt
localstack_ext.egg-info/entry_points.txt
localstack_ext.egg-info/plux.json
localstack_ext.egg-info/requires.txt
localstack_ext.egg-info/top_level.txt