Metadata-Version: 2.2
Name: localstack-ext
Version: 4.1.1
Summary: Extensions for LocalStack
Author-email: LocalStack Team <info@localstack.cloud>
License: Proprietary
Project-URL: Homepage, https://localstack.cloud
Project-URL: Documentation, https://docs.localstack.cloud
Project-URL: Issues, https://github.com/localstack/localstack/issues
Classifier: Programming Language :: Python :: 3
Classifier: Programming Language :: Python :: 3.11
Classifier: License :: Other/Proprietary License
Classifier: Topic :: Internet
Classifier: Topic :: Software Development :: Testing
Classifier: Topic :: System :: Emulators
Requires-Python: >=3.9
Requires-Dist: dill>=0.3.2
Requires-Dist: dnslib>=0.9.10
Requires-Dist: dnspython>=1.16.0
Requires-Dist: packaging
Requires-Dist: build
Requires-Dist: plux>=1.10.0
Requires-Dist: localstack-core==4.1.1
Requires-Dist: pyotp>=2.9.0
Requires-Dist: python-jose[cryptography]>=3.1.0
Requires-Dist: requests>=2.20.0
Requires-Dist: python-dateutil>=2.8
Requires-Dist: tabulate
Requires-Dist: windows-curses; platform_system == "Windows"
Provides-Extra: runtime
Requires-Dist: amazon.ion>=0.9.3; extra == "runtime"
Requires-Dist: avro>=1.11.0; extra == "runtime"
Requires-Dist: aws-encryption-sdk>=3.1.0; extra == "runtime"
Requires-Dist: aws-json-term-matcher>=0.1.5; extra == "runtime"
Requires-Dist: dirtyjson>=1.0.7; extra == "runtime"
Requires-Dist: distro; extra == "runtime"
Requires-Dist: docker-registry-client>=0.5.2; extra == "runtime"
Requires-Dist: dulwich>=0.19.16; extra == "runtime"
Requires-Dist: graphql-core>=3.0.3; extra == "runtime"
Requires-Dist: janus>=0.5.0; extra == "runtime"
Requires-Dist: jsonpatch>=1.32; extra == "runtime"
Requires-Dist: kafka-python; extra == "runtime"
Requires-Dist: confluent-kafka; extra == "runtime"
Requires-Dist: kubernetes>=21.7.0; extra == "runtime"
Requires-Dist: libvirt-python==10.2.0; extra == "runtime"
Requires-Dist: localstack-core[runtime]==4.1.1; extra == "runtime"
Requires-Dist: paho-mqtt>=1.5; extra == "runtime"
Requires-Dist: parquet[snappy]>=1.3.1; extra == "runtime"
Requires-Dist: parse>=1.19.0; extra == "runtime"
Requires-Dist: pg8000>=1.10; extra == "runtime"
Requires-Dist: postgres>=2.2.2; extra == "runtime"
Requires-Dist: postgresql-proxy>=0.2.0; extra == "runtime"
Requires-Dist: presto-python-client>=0.7.0; extra == "runtime"
Requires-Dist: pycdlib>=1.14.0; extra == "runtime"
Requires-Dist: pyftpdlib>=1.5.6; extra == "runtime"
Requires-Dist: pyhive[hive_pure_sasl]>=0.7.0; extra == "runtime"
Requires-Dist: pure-sasl>=0.6.2; extra == "runtime"
Requires-Dist: thrift>=0.10.0; extra == "runtime"
Requires-Dist: thrift_sasl>=0.1.0; extra == "runtime"
Requires-Dist: pyion2json>=0.0.2; extra == "runtime"
Requires-Dist: PyJWT>=1.7.0; extra == "runtime"
Requires-Dist: pymysql; extra == "runtime"
Requires-Dist: mysql-replication; extra == "runtime"
Requires-Dist: pproxy-ext>=2.7.9; extra == "runtime"
Requires-Dist: pyqldb~=3.2; extra == "runtime"
Requires-Dist: python-snappy>=0.6; extra == "runtime"
Requires-Dist: readerwriterlock>=1.0.7; extra == "runtime"
Requires-Dist: redis>=5.0; extra == "runtime"
Requires-Dist: rsa>=4.0; extra == "runtime"
Requires-Dist: sql-metadata>=2.6.0; extra == "runtime"
Requires-Dist: sqlglot[rs]; extra == "runtime"
Requires-Dist: srp-ext>=1.0.7.1; extra == "runtime"
Requires-Dist: testing.common.database>=1.1.0; extra == "runtime"
Requires-Dist: tornado>=6.0; extra == "runtime"
Requires-Dist: warrant-ext>=0.6.2; extra == "runtime"
Requires-Dist: websockets<14,>=8.1; extra == "runtime"
Requires-Dist: Whoosh>=2.7.4; extra == "runtime"
Provides-Extra: test
Requires-Dist: localstack-ext[runtime]; extra == "test"
Requires-Dist: aiohttp; extra == "test"
Requires-Dist: async-timeout; extra == "test"
Requires-Dist: awsiotsdk; extra == "test"
Requires-Dist: awswrangler>=3.5.2; extra == "test"
Requires-Dist: aws_xray_sdk>=2.4.2; extra == "test"
Requires-Dist: coverage[toml]>=5.0.0; extra == "test"
Requires-Dist: deepdiff>=5.5.0; extra == "test"
Requires-Dist: gremlinpython; extra == "test"
Requires-Dist: jws>=0.1.3; extra == "test"
Requires-Dist: localstack-core[test]==4.1.1; extra == "test"
Requires-Dist: msal; extra == "test"
Requires-Dist: msal-extensions; extra == "test"
Requires-Dist: msrest; extra == "test"
Requires-Dist: neo4j; extra == "test"
Requires-Dist: nest-asyncio>=1.4.1; extra == "test"
Requires-Dist: paramiko; extra == "test"
Requires-Dist: portalocker; extra == "test"
Requires-Dist: pre-commit>=3.5.0; extra == "test"
Requires-Dist: pyarrow; extra == "test"
Requires-Dist: PyAthena[Pandas]; extra == "test"
Requires-Dist: pymongo; extra == "test"
Requires-Dist: pymssql>=2.2.8; extra == "test"
Requires-Dist: pytest-instafail>=0.4.2; extra == "test"
Requires-Dist: ruff>=0.1.0; extra == "test"
Requires-Dist: redshift_connector; extra == "test"
Requires-Dist: stomp.py>=8.0.1; extra == "test"
Requires-Dist: mysql-connector-python; extra == "test"
Requires-Dist: python-terraform; extra == "test"
Requires-Dist: aws-cdk-lib>=2.88.0; extra == "test"
Requires-Dist: aws_cdk.aws_neptune_alpha; extra == "test"
Requires-Dist: aws_cdk.aws_redshift_alpha; extra == "test"
Requires-Dist: awsiotsdk; extra == "test"
Requires-Dist: aws-cdk.aws-cognito-identitypool-alpha; extra == "test"
Requires-Dist: playwright; extra == "test"
Requires-Dist: pytest-playwright; extra == "test"
Provides-Extra: package
Requires-Dist: python-minifier<2.11.3; extra == "package"
Provides-Extra: typehint
Requires-Dist: localstack-ext[test]; extra == "typehint"
Requires-Dist: boto3-stubs[acm,amplify,apigateway,apigatewayv2,appconfig,appsync,athena,autoscaling,backup,batch,bedrock,bedrock-runtime,ce,cloudcontrol,cloudformation,cloudfront,cloudtrail,cloudwatch,codecommit,cognito-identity,cognito-idp,dms,docdb,dynamodb,dynamodbstreams,ec2,ecr,ecs,efs,eks,elasticache,elasticbeanstalk,elbv2,emr,emr-serverless,es,events,firehose,fis,glacier,glue,iam,iot,iot-data,iotanalytics,iotwireless,kafka,kinesis,kinesisanalytics,kinesisanalyticsv2,kms,lakeformation,lamb
